scDCF/__init__.py
scDCF/__main__.py
scDCF/analysis.py
scDCF/cell_metadata.py
scDCF/control_genes.py
scDCF/dependencies.py
scDCF/main.py
scDCF/parallel.py
scDCF/post_analysis.py
scDCF/trait_association.py
scDCF/utils.py
scDCF/docs/methods.md
scDCF/docs/output_structure.md
scDCF/docs/scDCF_workflow.png
scdcf-0.1.15.dist-info/METADATA
scdcf-0.1.15.dist-info/WHEEL
scdcf-0.1.15.dist-info/entry_points.txt
scdcf-0.1.15.dist-info/top_level.txt
scdcf-0.1.15.dist-info/RECORD
