Metadata-Version: 2.4
Name: scDCF
Version: 0.1.15
Summary: A Framework for Detecting Disease-associated Cells in Single-cell RNA-seq Leveraging Healthy Reference Panels and GWAS Findings
Home-page: https://github.com/ZHANGCaicai581/scDCF
Author: Caicai Zhang
Author-email: Caicai Zhang <u3009162@connect.hku.hk>
License: MIT
Project-URL: Homepage, https://github.com/ZHANGCaicai581/scDCF
Project-URL: Repository, https://github.com/ZHANGCaicai581/scDCF
Project-URL: Issues, https://github.com/ZHANGCaicai581/scDCF/issues
Keywords: single-cell,genomics,GWAS,bioinformatics,disease,cell-type
Classifier: Development Status :: 4 - Beta
Classifier: Intended Audience :: Science/Research
Classifier: Operating System :: OS Independent
Classifier: Programming Language :: Python :: 3
Classifier: Programming Language :: Python :: 3.9
Classifier: Programming Language :: Python :: 3.10
Classifier: Programming Language :: Python :: 3.11
Classifier: Topic :: Scientific/Engineering :: Bio-Informatics
Requires-Python: >=3.9
Requires-Dist: scanpy>=1.9.0
Requires-Dist: pandas>=1.3.0
Requires-Dist: numpy>=1.21.0
Requires-Dist: scipy>=1.7.0
Requires-Dist: matplotlib>=3.3.0
Requires-Dist: seaborn>=0.11.0
Requires-Dist: tqdm>=4.60.0
Requires-Dist: statsmodels>=0.12.0
Requires-Dist: anndata>=0.8.0
Requires-Dist: numba>=0.56.0
Dynamic: author
Dynamic: home-page
Dynamic: requires-python
